nonebot_plugin_nsfw_detector-1.4.0.dist-info/METADATA
nonebot_plugin_nsfw_detector-1.4.0.dist-info/WHEEL
nonebot_plugin_nsfw_detector-1.4.0.dist-info/entry_points.txt
nonebot_plugin_nsfw_detector-1.4.0.dist-info/licenses/LICENSE
nonebot_plugin_nsfw_detector/__init__.py
nonebot_plugin_nsfw_detector/config.py
nonebot_plugin_nsfw_detector-1.4.0.dist-info/RECORD
