Metadata-Version: 2.1
Name: nonebot-plugin-nsfw-detector
Version: 1.4.0
Summary: 基于 nsfwpy.cn API 的 NoneBot2 NSFW 图片检测插件，自动检测群聊中的不当图片并进行相应处理
Keywords: nonebot,nonebot2,nsfw,detector,bot,qq
Author-Email: Msg-Lbo <msglbo@foxmail.com>
License: MIT
Classifier: Development Status :: 4 - Beta
Classifier: Framework :: Robot Framework
Classifier: Framework :: Robot Framework :: Library
Classifier: License :: OSI Approved :: MIT License
Classifier: Operating System :: OS Independent
Classifier: Programming Language :: Python :: 3
Classifier: Programming Language :: Python :: 3.8
Classifier: Programming Language :: Python :: 3.9
Classifier: Programming Language :: Python :: 3.10
Classifier: Programming Language :: Python :: 3.11
Classifier: Programming Language :: Python :: 3.12
Classifier: Topic :: Communications :: Chat
Classifier: Topic :: Software Development :: Libraries :: Python Modules
Project-URL: Homepage, https://github.com/Msg-Lbo/nonebot-plugin-nsfw-detector
Project-URL: Repository, https://github.com/Msg-Lbo/nonebot-plugin-nsfw-detector
Project-URL: Documentation, https://github.com/Msg-Lbo/nonebot-plugin-nsfw-detector#readme
Project-URL: Changelog, https://github.com/Msg-Lbo/nonebot-plugin-nsfw-detector/releases
Requires-Python: >=3.8
Requires-Dist: nonebot2>=2.0.0
Requires-Dist: nonebot-adapter-onebot>=2.0.0
Requires-Dist: httpx>=0.24.0
